tabcamel/__init__.py
tabcamel/data/__init__.py
tabcamel/data/dataset.py
tabcamel/data/stype.py
tabcamel/data/transform.py
tabcamel/utils/__init__.py
tabcamel/utils/config.py
tabcamel/utils/dataframe.py
tabcamel/utils/loading.py
tabcamel-2025.8.10.dist-info/METADATA
tabcamel-2025.8.10.dist-info/WHEEL
tabcamel-2025.8.10.dist-info/licenses/LICENSE
tabcamel-2025.8.10.dist-info/RECORD
