Metadata-Version: 2.4
Name: tabcamel
Version: 2025.8.10
Summary: TabCamel: A DataFrame-focused solution for tabular datasets in machine learning workflows
Author-email: Xiangjian Jiang <silencejiang12138@gmail.com>
License:                                  Apache License
License-File: LICENSE
Keywords: dataframe,machine learning,tabular data
Classifier: License :: OSI Approved :: Apache Software License
Classifier: Programming Language :: Python :: 3
Classifier: Programming Language :: Python :: 3.10
Requires-Python: >=3.10
Requires-Dist: bnlearn
Requires-Dist: cloudpickle
Requires-Dist: flake8
Requires-Dist: ipykernel
Requires-Dist: myst-parser
Requires-Dist: pgmpy==1.0.0
Requires-Dist: pylint
Requires-Dist: pytest
Requires-Dist: setuptools==75.1.0
Requires-Dist: sphinx
Requires-Dist: sphinx-book-theme
Requires-Dist: sphinx-rtd-theme
Requires-Dist: ucimlrepo
Provides-Extra: dev
